{
  "lines": {
    "doubleClickToEdit": "Düzenlemek için çift tıklayın",
    "unit": "Birim",
    "descriptionTooltipText": "Bunlar satır bazlı kalem açıklamalarıdır. Maksimum karakter limiti 200'dür",
    "lineItemDescriptionPlaceholder": "Satır bazlı kalem açıklaması"
  },
  "notes": {
    "title": "Sipariş Notları",
    "description": "Sipariş için iç notlar ekleyin ve güncelleyin.",
    "placeholder": "Sipariş notunu girin",
    "noteLabel": "Sipariş Notu",
    "notesTooltipText": "Sipariş geneli açıklamalarıdır. Maksimum karakter limiti 100'dür",
    "addLineTooltip": "Açıklama satırı ekle",
    "linesHint": "Her satır PDF ve belge notlarında ayrı görünür.",
    "removeLine": "Satırı kaldır",
    "pageLabel": "Sayfa {{current}} / {{total}}",
    "saving": "Notlar kaydediliyor...",
    "maxLengthError": "Not alanı en fazla 100 karakter olabilir."
  },
  "erpOrder": {
    "title": "ERP Sipariş Listesi",
    "description": "Netsis üzerinde giriş yapan kullanıcı kapsamında görünen sipariş üst kayıtlarını ve kalemlerini izleyin.",
    "currentUserScope": "Giriş yapan kullanıcı esaslıdır",
    "searchPlaceholder": "Sipariş no, cari, plasiyer veya tarih ara...",
    "loading": "ERP siparişleri yükleniyor...",
    "loadError": "ERP siparişleri yüklenemedi.",
    "noData": "ERP siparişi bulunamadı.",
    "detailAction": "Detay",
    "detailTitle": "{{orderNo}} sipariş detayı",
    "unknownCustomer": "Cari adı yok",
    "lineCount": "{{count}} kalem",
    "linesLoading": "Sipariş kalemleri yükleniyor...",
    "lineLoadError": "Sipariş kalemleri yüklenemedi.",
    "noLines": "Bu sipariş için kalem bulunamadı.",
    "table": {
      "title": "Sipariş Üst Bilgileri",
      "branchCode": "Şube",
      "orderNo": "Sipariş No",
      "customerCode": "Cari Kodu",
      "customerName": "Cari Adı",
      "date": "Tarih",
      "deliveryDate": "Teslim Tarihi",
      "grossTotal": "Brüt Tutar",
      "vat": "KDV",
      "grandTotal": "Genel Toplam",
      "salesRepCode": "Plasiyer"
    },
    "lines": {
      "rowNo": "Sıra",
      "stockCode": "Stok Kodu",
      "stockName": "Stok Adı",
      "quantity": "Miktar",
      "unit": "Birim",
      "netPrice": "Net Fiyat",
      "vatRate": "KDV Oranı",
      "warehouseCode": "Depo"
    }
  },
  "header": {
    "ozelKod1": "Özel Kod 1",
    "ozelKod1Placeholder": "Özel Kod 1 seçin",
    "ozelKod2": "Özel Kod 2",
    "ozelKod2Placeholder": "Özel Kod 2 seçin",
    "specialCodeSearchPlaceholder": "Özel kod ara..."
  }
}
